setup.py
spendingizer/__init__.py
spendingizer_djmgrant-0.0.5.dist-info/METADATA
spendingizer_djmgrant-0.0.5.dist-info/WHEEL
spendingizer_djmgrant-0.0.5.dist-info/licenses/LICENSE
spendingizer_djmgrant-0.0.5.dist-info/RECORD
