Metadata-Version: 2.1
Name: spendingizer_djmgrant
Version: 0.0.5
Summary: A package to import and analyse persomal spending
Project-URL: Homepage, https://github.com/djmgrant/spendingizer
Project-URL: Bug Tracker, https://github.com/djmgrant/spendingizer/issues
Author-email: D Grant <djmgrant@gmail.com>
License: MIT License
Classifier: License :: OSI Approved :: MIT License
Classifier: Operating System :: OS Independent
Classifier: Programming Language :: Python :: 3
Requires-Python: >=3.7
Requires-Dist: pandas
Requires-Dist: plotly-express
